romt/__init__.py
romt/base.py
romt/cli.py
romt/common.py
romt/crate.py
romt/dist.py
romt/download.py
romt/error.py
romt/integrity.py
romt/manifest.py
romt/py.typed
romt/rustup.py
romt/serve.py
romt/signature.py
romt/toolchain.py
romt-0.9.0.dist-info/LICENSE.rst
romt-0.9.0.dist-info/METADATA
romt-0.9.0.dist-info/WHEEL
romt-0.9.0.dist-info/entry_points.txt
romt-0.9.0.dist-info/RECORD
