Metadata-Version: 2.1
Name: romt
Version: 0.9.0
Summary: Romt (Rust Offline Mirror Tool) enables mirroring of Rust programming language tools and crates for use in an offline context.
Home-page: https://github.com/drmikehenry/romt
License: MIT
Keywords: Rust,mirror,toolchain,crates
Author: Michael Henry
Author-email: drmikehenry@drmikehenry.com
Requires-Python: >=3.9,<3.14
Classifier: Development Status :: 4 - Beta
Classifier: Environment :: Console
Classifier: License :: OSI Approved :: MIT License
Classifier: Programming Language :: Python :: 3
Classifier: Programming Language :: Python :: 3.9
Classifier: Programming Language :: Python :: 3.10
Classifier: Programming Language :: Python :: 3.11
Classifier: Programming Language :: Python :: 3.12
Classifier: Programming Language :: Python :: 3.13
Classifier: Programming Language :: Python :: 3 :: Only
Classifier: Topic :: Utilities
Requires-Dist: gitpython (>=3.1,<4.0)
Requires-Dist: httpx (>=0.28,<0.29)
Requires-Dist: python-gnupg (>=0.5,<0.6)
Requires-Dist: toml (>=0.10,<0.11)
Requires-Dist: trio (>=0.29,<0.30)
Project-URL: Repository, https://github.com/drmikehenry/romt
